{"name":"build-javascript","namedChunkGroups":{"polyfill":{"name":"polyfill","assets":[{"name":"webpack-runtime-4cc1dcf7c4c7c3540eaf.js","size":5196},{"name":"polyfill-4718f0fec20e0d09d7f5.js","size":85862}],"filteredAssets":0,"assetsSize":91058,"filteredAuxiliaryAssets":2,"auxiliaryAssetsSize":228365},"app":{"name":"app","assets":[{"name":"webpack-runtime-4cc1dcf7c4c7c3540eaf.js","size":5196},{"name":"framework-c9d1d3c0dcdb956d62a6.js","size":130570},{"name":"app-d11e9718564e95084bec.js","size":71065}],"filteredAssets":0,"assetsSize":206831,"filteredAuxiliaryAssets":3,"auxiliaryAssetsSize":671989},"component---src-pages-404-js":{"name":"component---src-pages-404-js","assets":[{"name":"framework-c9d1d3c0dcdb956d62a6.js","size":130570},{"name":"styles.caf9dcabd679def50dc4.css","size":5429},{"name":"commons-1e14abc9d62911e91440.js","size":86088},{"name":"b421bf2b7d991cff6f968f12e1ca54cf112e0d9c-00c7d03ab259b0905c05.js","size":15149},{"name":"component---src-pages-404-js-5448bf2f56e277493ec1.js","size":585}],"filteredAssets":0,"assetsSize":237821,"filteredAuxiliaryAssets":5,"auxiliaryAssetsSize":673813},"component---src-pages-index-js":{"name":"component---src-pages-index-js","assets":[{"name":"framework-c9d1d3c0dcdb956d62a6.js","size":130570},{"name":"styles.caf9dcabd679def50dc4.css","size":5429},{"name":"commons-1e14abc9d62911e91440.js","size":86088},{"name":"component---src-pages-index-js-85d0886154b06ebd89c8.js","size":619}],"filteredAssets":0,"assetsSize":222706,"filteredAuxiliaryAssets":4,"auxiliaryAssetsSize":609848},"component---src-templates-using-dsg-js":{"name":"component---src-templates-using-dsg-js","assets":[{"name":"framework-c9d1d3c0dcdb956d62a6.js","size":130570},{"name":"styles.caf9dcabd679def50dc4.css","size":5429},{"name":"commons-1e14abc9d62911e91440.js","size":86088},{"name":"b421bf2b7d991cff6f968f12e1ca54cf112e0d9c-00c7d03ab259b0905c05.js","size":15149},{"name":"component---src-templates-using-dsg-js-94e0b8f5997a8644d992.js","size":1529}],"filteredAssets":0,"assetsSize":238765,"filteredAuxiliaryAssets":5,"auxiliaryAssetsSize":676837}},"assetsByChunkName":{"polyfill":["webpack-runtime-4cc1dcf7c4c7c3540eaf.js","polyfill-4718f0fec20e0d09d7f5.js"],"app":["webpack-runtime-4cc1dcf7c4c7c3540eaf.js","framework-c9d1d3c0dcdb956d62a6.js","app-d11e9718564e95084bec.js"],"component---src-pages-404-js":["framework-c9d1d3c0dcdb956d62a6.js","styles.caf9dcabd679def50dc4.css","commons-1e14abc9d62911e91440.js","b421bf2b7d991cff6f968f12e1ca54cf112e0d9c-00c7d03ab259b0905c05.js","component---src-pages-404-js-5448bf2f56e277493ec1.js"],"component---src-pages-index-js":["framework-c9d1d3c0dcdb956d62a6.js","styles.caf9dcabd679def50dc4.css","commons-1e14abc9d62911e91440.js","component---src-pages-index-js-85d0886154b06ebd89c8.js"],"component---src-templates-using-dsg-js":["framework-c9d1d3c0dcdb956d62a6.js","styles.caf9dcabd679def50dc4.css","commons-1e14abc9d62911e91440.js","b421bf2b7d991cff6f968f12e1ca54cf112e0d9c-00c7d03ab259b0905c05.js","component---src-templates-using-dsg-js-94e0b8f5997a8644d992.js"]},"childAssetsByChunkName":{}}